fredpy/__init__.py
fredpy-3.2.9.dist-info/LICENSE
fredpy-3.2.9.dist-info/METADATA
fredpy-3.2.9.dist-info/WHEEL
fredpy-3.2.9.dist-info/top_level.txt
fredpy-3.2.9.dist-info/RECORD
